HttpSocket/HttpSocket.py
HttpSocket/__init__.py
HttpSocket-1.0.0.dist-info/LICENSE
HttpSocket-1.0.0.dist-info/METADATA
HttpSocket-1.0.0.dist-info/WHEEL
HttpSocket-1.0.0.dist-info/top_level.txt
HttpSocket-1.0.0.dist-info/RECORD
