Metadata-Version: 2.1
Name: HttpSocket
Version: 1.0.0
Summary: a library for sending http but with socket!
Home-page: https://github.com/BlackSnowDot/HttpSocket
Author: BlackSnowDot
Author-email: 
License: MIT
Platform: UNKNOWN
License-File: LICENSE
